tests/__init__.py
tests/algorithm_module.py
tests/test_deserialization.py
tests/test_docker_wrapper.py
tests/test_serialization.py
tests/algorithm/__init__.py
tests/algorithm/test___init__.py
tests/base/__init__.py
vantage6/algorithm/client/__build__
vantage6/algorithm/client/__init__.py
vantage6/algorithm/client/_version.py
vantage6/algorithm/tools/__init__.py
vantage6/algorithm/tools/decorators.py
vantage6/algorithm/tools/exceptions.py
vantage6/algorithm/tools/mock_client.py
vantage6/algorithm/tools/util.py
vantage6/algorithm/tools/wrap.py
vantage6/algorithm/tools/wrappers.py
vantage6/algorithm/tools/preprocessing/__init__.py
vantage6/algorithm/tools/preprocessing/functions.py
vantage6_algorithm_tools-4.13.6.dist-info/METADATA
vantage6_algorithm_tools-4.13.6.dist-info/WHEEL
vantage6_algorithm_tools-4.13.6.dist-info/top_level.txt
vantage6_algorithm_tools-4.13.6.dist-info/RECORD
